{
  "war": [
    {
      "war_num": "677.0",
      "war_name": "Russian Civil War",
      "war_type_code": "4",
      "war_type": "Intra-State War",
      "war_subtype": "Civil War (for central control)",
      "participants": "7",
      "start_date": "1917-12-09",
      "start_year": "1917",
      "end_date": "1920-11-20",
      "end_year": "1920",
      "lagging_war": "-8",
      "leading_war": "-8",
      "ongoing_conflict": "0",
      "start_date_estimated": "0",
      "end_date_estimated": "0"
    }
  ],
  "nodes": [
    {
      "id": "0",
      "war_type_code": "4",
      "c_code": "-8",
      "participant": "Anti-Bolsheviks",
      "side": "2.0",
      "battle_deaths_z": "325000.0",
      "battle_deaths_estimated": "0",
      "start_year": "1917",
      "start_date": "1917-12-09",
      "end_year": "1920.0",
      "end_date": "1920-11-20",
      "ongoing_conflict": "0",
      "start_date_estimated": "0",
      "end_date_estimated": "0",
      "days_not_at_war_z": "0.0",
      "lagging_war": "-8",
      "leading_war": "-8",
      "deaths_both_sides": "1029225.0",
      "peak_forces_available_z": "nan",
      "peak_battle_forces_z": "500000.0",
      "terrorism_deaths_x": "nan",
      "mid_dyads_x": "nan",
      "mid_dyads_initiated_x": "nan",
      "mid_dyads_targeted_x": "nan",
      "mid_dyads_joined_x": "nan",
      "allied_countries_x": "nan",
      "trade_countries_x": "nan",
      "money_flow_in_x": "nan",
      "money_flow_out_x": "nan",
      "imports_x": "nan",
      "exports_x": "nan",
      "military_expenditure_x": "nan",
      "military_personnel_x": "nan",
      "iron_steel_production_x": "nan",
      "energy_consumption_x": "nan",
      "population_x": "nan",
      "urban_population_x": "nan",
      "urban_population_growth_rate_x": "nan",
      "cinc_score_x": "nan",
      "land_mass_exchange_gain_x": "nan",
      "population_exchange_gain_x": "nan",
      "land_mass_exchange_loss_x": "nan",
      "population_exchange_loss_x": "nan",
      "refugees_originated_x": "nan",
      "refugees_hosted_x": "nan",
      "internally_displaced_persons_x": "nan",
      "concurrent_wars_x": "nan",
      "terrorism_deaths_y": "nan",
      "mid_dyads_y": "nan",
      "mid_dyads_initiated_y": "nan",
      "mid_dyads_targeted_y": "nan",
      "mid_dyads_joined_y": "nan",
      "allied_countries_y": "nan",
      "trade_countries_y": "nan",
      "money_flow_in_y": "nan",
      "money_flow_out_y": "nan",
      "imports_y": "nan",
      "exports_y": "nan",
      "military_expenditure_y": "nan",
      "military_personnel_y": "nan",
      "iron_steel_production_y": "nan",
      "energy_consumption_y": "nan",
      "population_y": "nan",
      "urban_population_y": "nan",
      "urban_population_growth_rate_y": "nan",
      "cinc_score_y": "nan",
      "land_mass_exchange_gain_y": "nan",
      "population_exchange_gain_y": "nan",
      "land_mass_exchange_loss_y": "nan",
      "population_exchange_loss_y": "nan",
      "refugees_originated_y": "nan",
      "refugees_hosted_y": "nan",
      "internally_displaced_persons_y": "nan",
      "concurrent_wars_y": "nan",
      "terrorism_deaths_z": "nan",
      "mid_dyads_z": "nan",
      "mid_dyads_initiated_z": "nan",
      "mid_dyads_targeted_z": "nan",
      "mid_dyads_joined_z": "nan",
      "allied_countries_z": "nan",
      "trade_countries_z": "nan",
      "money_flow_in_z": "nan",
      "money_flow_out_z": "nan",
      "imports_z": "nan",
      "exports_z": "nan",
      "military_expenditure_z": "nan",
      "military_personnel_z": "nan",
      "iron_steel_production_z": "nan",
      "energy_consumption_z": "nan",
      "population_z": "nan",
      "urban_population_z": "nan",
      "urban_population_growth_rate_z": "nan",
      "cinc_score_z": "nan",
      "land_mass_exchange_gain_z": "nan",
      "population_exchange_gain_z": "nan",
      "land_mass_exchange_loss_z": "nan",
      "population_exchange_loss_z": "nan",
      "refugees_originated_z": "nan",
      "refugees_hosted_z": "nan",
      "internally_displaced_persons_z": "nan",
      "concurrent_wars_z": "nan"
    },
    {
      "id": "1",
      "war_type_code": "4",
      "c_code": "2",
      "participant": "United States of America",
      "side": "2.0",
      "battle_deaths_z": "275.0",
      "battle_deaths_estimated": "0",
      "start_year": "1918",
      "start_date": "1918-06-23",
      "end_year": "1920.0",
      "end_date": "1920-04-20",
      "ongoing_conflict": "0",
      "start_date_estimated": "0",
      "end_date_estimated": "0",
      "days_not_at_war_z": "0.0",
      "lagging_war": "-8",
      "leading_war": "-8",
      "deaths_both_sides": "nan",
      "peak_forces_available_z": "2897000.0",
      "peak_battle_forces_z": "13200.0",
      "terrorism_deaths_x": "0.0",
      "mid_dyads_x": "4.0",
      "mid_dyads_initiated_x": "0.0",
      "mid_dyads_targeted_x": "1.0",
      "mid_dyads_joined_x": "3.0",
      "allied_countries_x": "0.0",
      "trade_countries_x": "1.0",
      "money_flow_in_x": "50000000.0",
      "money_flow_out_x": "34290000.0",
      "imports_x": "3105.0",
      "exports_x": "6402.0",
      "military_expenditure_x": "7014226000.0",
      "military_personnel_x": "2897000.0",
      "iron_steel_production_x": "90352000000.0",
      "energy_consumption_x": "1487850000000.0",
      "population_x": "103208000.0",
      "urban_population_x": "26020000.0",
      "urban_population_growth_rate_x": "0.0",
      "cinc_score_x": "0.29487148",
      "land_mass_exchange_gain_x": "0.0",
      "population_exchange_gain_x": "0.0",
      "land_mass_exchange_loss_x": "0.0",
      "population_exchange_loss_x": "0.0",
      "refugees_originated_x": "0.0",
      "refugees_hosted_x": "0.0",
      "internally_displaced_persons_x": "0.0",
      "concurrent_wars_x": "3.0",
      "terrorism_deaths_y": "0.0",
      "mid_dyads_y": "2.0",
      "mid_dyads_initiated_y": "1.0",
      "mid_dyads_targeted_y": "0.0",
      "mid_dyads_joined_y": "1.0",
      "allied_countries_y": "0.0",
      "trade_countries_y": "47.0",
      "money_flow_in_y": "4662060000.0",
      "money_flow_out_y": "8035440000.0",
      "imports_y": "5278.48",
      "exports_y": "8228.01",
      "military_expenditure_y": "1657118000.0",
      "military_personnel_y": "343000.0",
      "iron_steel_production_y": "85618000000.0",
      "energy_consumption_y": "1487616000000.0",
      "population_y": "106461000.0",
      "urban_population_y": "27428000.0",
      "urban_population_growth_rate_y": "0.0",
      "cinc_score_y": "0.28956637",
      "land_mass_exchange_gain_y": "0.0",
      "population_exchange_gain_y": "0.0",
      "land_mass_exchange_loss_y": "0.0",
      "population_exchange_loss_y": "0.0",
      "refugees_originated_y": "0.0",
      "refugees_hosted_y": "0.0",
      "internally_displaced_persons_y": "0.0",
      "concurrent_wars_y": "1.0",
      "terrorism_deaths_z": "0.0",
      "mid_dyads_z": "2.67",
      "mid_dyads_initiated_z": "0.67",
      "mid_dyads_targeted_z": "0.33",
      "mid_dyads_joined_z": "1.67",
      "allied_countries_z": "0.0",
      "trade_countries_z": "20.0",
      "money_flow_in_z": "1963870000.0",
      "money_flow_out_z": "3583490000.0",
      "imports_z": "4125.49",
      "exports_z": "7596.34",
      "military_expenditure_z": "6629713330.0",
      "military_personnel_z": "1471000.0",
      "iron_steel_production_z": "82142000000.0",
      "energy_consumption_z": "1424084000000.0",
      "population_z": "104727670.0",
      "urban_population_z": "26723670.0",
      "urban_population_growth_rate_z": "0.0",
      "cinc_score_z": "0.32190706333333335",
      "land_mass_exchange_gain_z": "0.0",
      "population_exchange_gain_z": "0.0",
      "land_mass_exchange_loss_z": "0.0",
      "population_exchange_loss_z": "0.0",
      "refugees_originated_z": "0.0",
      "refugees_hosted_z": "0.0",
      "internally_displaced_persons_z": "0.0",
      "concurrent_wars_z": "2.0"
    },
    {
      "id": "2",
      "war_type_code": "4",
      "c_code": "200",
      "participant": "United Kingdom",
      "side": "2.0",
      "battle_deaths_z": "350.0",
      "battle_deaths_estimated": "0",
      "start_year": "1918",
      "start_date": "1918-06-23",
      "end_year": "1920.0",
      "end_date": "1920-03-15",
      "ongoing_conflict": "0",
      "start_date_estimated": "0",
      "end_date_estimated": "0",
      "days_not_at_war_z": "0.0",
      "lagging_war": "-8",
      "leading_war": "-8",
      "deaths_both_sides": "nan",
      "peak_forces_available_z": "4222000.0",
      "peak_battle_forces_z": "44600.0",
      "terrorism_deaths_x": "0.0",
      "mid_dyads_x": "7.0",
      "mid_dyads_initiated_x": "1.0",
      "mid_dyads_targeted_x": "0.0",
      "mid_dyads_joined_x": "6.0",
      "allied_countries_x": "5.0",
      "trade_countries_x": "2.0",
      "money_flow_in_x": "305800000.0",
      "money_flow_out_x": "190460000.0",
      "imports_x": "6266.67",
      "exports_x": "2385.71",
      "military_expenditure_x": "8104264000.0",
      "military_personnel_x": "4222000.0",
      "iron_steel_production_x": "19384000000.0",
      "energy_consumption_x": "413466000000.0",
      "population_x": "43116000.0",
      "urban_population_x": "18271000.0",
      "urban_population_growth_rate_x": "0.0",
      "cinc_score_x": "0.14279717",
      "land_mass_exchange_gain_x": "0.0",
      "population_exchange_gain_x": "0.0",
      "land_mass_exchange_loss_x": "0.0",
      "population_exchange_loss_x": "0.0",
      "refugees_originated_x": "0.0",
      "refugees_hosted_x": "0.0",
      "internally_displaced_persons_x": "0.0",
      "concurrent_wars_x": "2.0",
      "terrorism_deaths_y": "0.0",
      "mid_dyads_y": "7.0",
      "mid_dyads_initiated_y": "4.0",
      "mid_dyads_targeted_y": "0.0",
      "mid_dyads_joined_y": "3.0",
      "allied_countries_y": "2.0",
      "trade_countries_y": "47.0",
      "money_flow_in_y": "6559360000.0",
      "money_flow_out_y": "4551700000.0",
      "imports_y": "7772.73",
      "exports_y": "6045.45",
      "military_expenditure_y": "1475661000.0",
      "military_personnel_y": "596000.0",
      "iron_steel_production_y": "18424000000.0",
      "energy_consumption_y": "426494000000.0",
      "population_y": "46472000.0",
      "urban_population_y": "18412000.0",
      "urban_population_growth_rate_y": "0.0",
      "cinc_score_y": "0.12763593",
      "land_mass_exchange_gain_y": "0.0",
      "population_exchange_gain_y": "0.0",
      "land_mass_exchange_loss_y": "17848135.0",
      "population_exchange_loss_y": "17848135.0",
      "refugees_originated_y": "0.0",
      "refugees_hosted_y": "0.0",
      "internally_displaced_persons_y": "0.0",
      "concurrent_wars_y": "4.0",
      "terrorism_deaths_z": "0.0",
      "mid_dyads_z": "6.33",
      "mid_dyads_initiated_z": "2.33",
      "mid_dyads_targeted_z": "0.0",
      "mid_dyads_joined_z": "4.0",
      "allied_countries_z": "3.0",
      "trade_countries_z": "20.0",
      "money_flow_in_z": "2608350000.0",
      "money_flow_out_z": "2259770000.0",
      "imports_z": "7079.09",
      "exports_z": "3989.38",
      "military_expenditure_z": "3441711330.0",
      "military_personnel_z": "2050330.0",
      "iron_steel_production_z": "17950000000.0",
      "energy_consumption_z": "414500660000.0",
      "population_z": "44729000.0",
      "urban_population_z": "18346330.0",
      "urban_population_growth_rate_z": "0.0",
      "cinc_score_z": "0.12712489333333335",
      "land_mass_exchange_gain_z": "0.0",
      "population_exchange_gain_z": "0.0",
      "land_mass_exchange_loss_z": "8867605.5",
      "population_exchange_loss_z": "8867605.5",
      "refugees_originated_z": "0.0",
      "refugees_hosted_z": "0.0",
      "internally_displaced_persons_z": "0.0",
      "concurrent_wars_z": "3.0"
    },
    {
      "id": "3",
      "war_type_code": "4",
      "c_code": "220",
      "participant": "France",
      "side": "2.0",
      "battle_deaths_z": "50.0",
      "battle_deaths_estimated": "0",
      "start_year": "1918",
      "start_date": "1918-06-23",
      "end_year": "1919.0",
      "end_date": "1919-09-30",
      "ongoing_conflict": "0",
      "start_date_estimated": "0",
      "end_date_estimated": "0",
      "days_not_at_war_z": "0.0",
      "lagging_war": "-8",
      "leading_war": "-8",
      "deaths_both_sides": "nan",
      "peak_forces_available_z": "5277000.0",
      "peak_battle_forces_z": "13600.0",
      "terrorism_deaths_x": "0.0",
      "mid_dyads_x": "6.0",
      "mid_dyads_initiated_x": "1.0",
      "mid_dyads_targeted_x": "0.0",
      "mid_dyads_joined_x": "5.0",
      "allied_countries_x": "3.0",
      "trade_countries_x": "0.0",
      "money_flow_in_x": "0.0",
      "money_flow_out_x": "0.0",
      "imports_x": "3971.87",
      "exports_x": "840.99",
      "military_expenditure_x": "7708000000.0",
      "military_personnel_x": "5277000.0",
      "iron_steel_production_x": "3600000000.0",
      "energy_consumption_x": "83232000000.0",
      "population_x": "32830000.0",
      "urban_population_x": "5893000.0",
      "urban_population_growth_rate_x": "0.0",
      "cinc_score_x": "0.088411272",
      "land_mass_exchange_gain_x": "0.0",
      "population_exchange_gain_x": "0.0",
      "land_mass_exchange_loss_x": "0.0",
      "population_exchange_loss_x": "0.0",
      "refugees_originated_x": "0.0",
      "refugees_hosted_x": "0.0",
      "internally_displaced_persons_x": "0.0",
      "concurrent_wars_x": "1.0",
      "terrorism_deaths_y": "0.0",
      "mid_dyads_y": "5.0",
      "mid_dyads_initiated_y": "2.0",
      "mid_dyads_targeted_y": "0.0",
      "mid_dyads_joined_y": "3.0",
      "allied_countries_y": "0.0",
      "trade_countries_y": "40.0",
      "money_flow_in_y": "3811970000.0",
      "money_flow_out_y": "621490000.0",
      "imports_y": "4897.93",
      "exports_y": "1625.39",
      "military_expenditure_y": "634729000.0",
      "military_personnel_y": "2364000.0",
      "iron_steel_production_y": "2586000000.0",
      "energy_consumption_y": "88668000000.0",
      "population_y": "31970000.0",
      "urban_population_y": "5889000.0",
      "urban_population_growth_rate_y": "0.0",
      "cinc_score_y": "0.061298519",
      "land_mass_exchange_gain_y": "764070.0",
      "population_exchange_gain_y": "764070.0",
      "land_mass_exchange_loss_y": "0.0",
      "population_exchange_loss_y": "0.0",
      "refugees_originated_y": "0.0",
      "refugees_hosted_y": "0.0",
      "internally_displaced_persons_y": "0.0",
      "concurrent_wars_y": "2.0",
      "terrorism_deaths_z": "0.0",
      "mid_dyads_z": "5.5",
      "mid_dyads_initiated_z": "1.5",
      "mid_dyads_targeted_z": "0.0",
      "mid_dyads_joined_z": "4.0",
      "allied_countries_z": "3.0",
      "trade_countries_z": "40.0",
      "money_flow_in_z": "3811970000.0",
      "money_flow_out_z": "621490000.0",
      "imports_z": "4434.9",
      "exports_z": "1233.19",
      "military_expenditure_z": "4171364500.0",
      "military_personnel_z": "3820500.0",
      "iron_steel_production_z": "3093000000.0",
      "energy_consumption_z": "85950000000.0",
      "population_z": "32400000.0",
      "urban_population_z": "5891000.0",
      "urban_population_growth_rate_z": "0.0",
      "cinc_score_z": "0.0748548955",
      "land_mass_exchange_gain_z": "764070.0",
      "population_exchange_gain_z": "764070.0",
      "land_mass_exchange_loss_z": "0.0",
      "population_exchange_loss_z": "0.0",
      "refugees_originated_z": "0.0",
      "refugees_hosted_z": "0.0",
      "internally_displaced_persons_z": "0.0",
      "concurrent_wars_z": "1.5"
    },
    {
      "id": "4",
      "war_type_code": "4",
      "c_code": "365",
      "participant": "Russia",
      "side": "1.0",
      "battle_deaths_z": "702000.0",
      "battle_deaths_estimated": "0",
      "start_year": "1917",
      "start_date": "1917-12-09",
      "end_year": "1920.0",
      "end_date": "1920-11-20",
      "ongoing_conflict": "0",
      "start_date_estimated": "0",
      "end_date_estimated": "0",
      "days_not_at_war_z": "0.0",
      "lagging_war": "-8",
      "leading_war": "-8",
      "deaths_both_sides": "1029225.0",
      "peak_forces_available_z": "5500000.0",
      "peak_battle_forces_z": "2000000.0",
      "terrorism_deaths_x": "0.0",
      "mid_dyads_x": "6.0",
      "mid_dyads_initiated_x": "0.0",
      "mid_dyads_targeted_x": "2.0",
      "mid_dyads_joined_x": "4.0",
      "allied_countries_x": "5.0",
      "trade_countries_x": "1.0",
      "money_flow_in_x": "43870000.0",
      "money_flow_out_x": "8369999.999999999",
      "imports_x": "0.0",
      "exports_x": "0.0",
      "military_expenditure_x": "4040000000.0",
      "military_personnel_x": "9050000.0",
      "iron_steel_production_x": "6160000000.0",
      "energy_consumption_x": "86566000000.0",
      "population_x": "184600000.0",
      "urban_population_x": "6471000.0",
      "urban_population_growth_rate_x": "0.0",
      "cinc_score_x": "0.11721399",
      "land_mass_exchange_gain_x": "0.0",
      "population_exchange_gain_x": "0.0",
      "land_mass_exchange_loss_x": "325534.0",
      "population_exchange_loss_x": "325534.0",
      "refugees_originated_x": "0.0",
      "refugees_hosted_x": "0.0",
      "internally_displaced_persons_x": "0.0",
      "concurrent_wars_x": "2.0",
      "terrorism_deaths_y": "0.0",
      "mid_dyads_y": "23.0",
      "mid_dyads_initiated_y": "12.0",
      "mid_dyads_targeted_y": "7.0",
      "mid_dyads_joined_y": "4.0",
      "allied_countries_y": "0.0",
      "trade_countries_y": "22.0",
      "money_flow_in_y": "100220000.0",
      "money_flow_out_y": "171210000.0",
      "imports_y": "19.58",
      "exports_y": "0.57",
      "military_expenditure_y": "1183426000.0",
      "military_personnel_y": "3050000.0",
      "iron_steel_production_y": "388000000.0",
      "energy_consumption_y": "26126000000.0",
      "population_y": "139675000.0",
      "urban_population_y": "4031000.0",
      "urban_population_growth_rate_y": "0.0",
      "cinc_score_y": "0.10320065",
      "land_mass_exchange_gain_y": "627612.0",
      "population_exchange_gain_y": "627612.0",
      "land_mass_exchange_loss_y": "0.0",
      "population_exchange_loss_y": "0.0",
      "refugees_originated_y": "0.0",
      "refugees_hosted_y": "0.0",
      "internally_displaced_persons_y": "0.0",
      "concurrent_wars_y": "7.0",
      "terrorism_deaths_z": "0.0",
      "mid_dyads_z": "18.0",
      "mid_dyads_initiated_z": "7.25",
      "mid_dyads_targeted_z": "6.0",
      "mid_dyads_joined_z": "4.75",
      "allied_countries_z": "5.0",
      "trade_countries_z": "7.25",
      "money_flow_in_z": "49910000.0",
      "money_flow_out_z": "51200000.0",
      "imports_z": "9.95",
      "exports_z": "3.06",
      "military_expenditure_z": "1724966500.0",
      "military_personnel_z": "3410250.0",
      "iron_steel_production_z": "1937500000.0",
      "energy_consumption_z": "44530000000.0",
      "population_z": "152497500.0",
      "urban_population_z": "4762750.0",
      "urban_population_growth_rate_z": "0.0",
      "cinc_score_z": "0.08021793825",
      "land_mass_exchange_gain_z": "0.0",
      "population_exchange_gain_z": "0.0",
      "land_mass_exchange_loss_z": "304040.33",
      "population_exchange_loss_z": "304040.33",
      "refugees_originated_z": "0.0",
      "refugees_hosted_z": "0.0",
      "internally_displaced_persons_z": "0.0",
      "concurrent_wars_z": "3.75"
    },
    {
      "id": "5",
      "war_type_code": "4",
      "c_code": "375",
      "participant": "Finland",
      "side": "2.0",
      "battle_deaths_z": "50.0",
      "battle_deaths_estimated": "0",
      "start_year": "1919",
      "start_date": "1919-04-15",
      "end_year": "1919.0",
      "end_date": "1919-04-30",
      "ongoing_conflict": "0",
      "start_date_estimated": "0",
      "end_date_estimated": "0",
      "days_not_at_war_z": "0.0",
      "lagging_war": "-8",
      "leading_war": "-8",
      "deaths_both_sides": "nan",
      "peak_forces_available_z": "38000.0",
      "peak_battle_forces_z": "25000.0",
      "terrorism_deaths_x": "0.0",
      "mid_dyads_x": "2.0",
      "mid_dyads_initiated_x": "1.0",
      "mid_dyads_targeted_x": "0.0",
      "mid_dyads_joined_x": "1.0",
      "allied_countries_x": "0.0",
      "trade_countries_x": "3.0",
      "money_flow_in_x": "0.0",
      "money_flow_out_x": "8750000.0",
      "imports_x": "49.21",
      "exports_x": "17.26",
      "military_expenditure_x": "7642000.0",
      "military_personnel_x": "38000.0",
      "iron_steel_production_x": "0.0",
      "energy_consumption_x": "204000000.0",
      "population_x": "3130000.0",
      "urban_population_x": "188000.0",
      "urban_population_growth_rate_x": "0.0",
      "cinc_score_x": "0.0013172193",
      "land_mass_exchange_gain_x": "0.0",
      "population_exchange_gain_x": "0.0",
      "land_mass_exchange_loss_x": "0.0",
      "population_exchange_loss_x": "0.0",
      "refugees_originated_x": "0.0",
      "refugees_hosted_x": "0.0",
      "internally_displaced_persons_x": "0.0",
      "concurrent_wars_x": "1.0",
      "terrorism_deaths_y": "0.0",
      "mid_dyads_y": "2.0",
      "mid_dyads_initiated_y": "1.0",
      "mid_dyads_targeted_y": "0.0",
      "mid_dyads_joined_y": "1.0",
      "allied_countries_y": "0.0",
      "trade_countries_y": "3.0",
      "money_flow_in_y": "0.0",
      "money_flow_out_y": "8750000.0",
      "imports_y": "49.21",
      "exports_y": "17.26",
      "military_expenditure_y": "7642000.0",
      "military_personnel_y": "38000.0",
      "iron_steel_production_y": "0.0",
      "energy_consumption_y": "204000000.0",
      "population_y": "3130000.0",
      "urban_population_y": "188000.0",
      "urban_population_growth_rate_y": "0.0",
      "cinc_score_y": "0.0013172193",
      "land_mass_exchange_gain_y": "0.0",
      "population_exchange_gain_y": "0.0",
      "land_mass_exchange_loss_y": "0.0",
      "population_exchange_loss_y": "0.0",
      "refugees_originated_y": "0.0",
      "refugees_hosted_y": "0.0",
      "internally_displaced_persons_y": "0.0",
      "concurrent_wars_y": "1.0",
      "terrorism_deaths_z": "0.0",
      "mid_dyads_z": "2.0",
      "mid_dyads_initiated_z": "1.0",
      "mid_dyads_targeted_z": "0.0",
      "mid_dyads_joined_z": "1.0",
      "allied_countries_z": "0.0",
      "trade_countries_z": "3.0",
      "money_flow_in_z": "0.0",
      "money_flow_out_z": "8750000.0",
      "imports_z": "49.21",
      "exports_z": "17.26",
      "military_expenditure_z": "7642000.0",
      "military_personnel_z": "38000.0",
      "iron_steel_production_z": "0.0",
      "energy_consumption_z": "204000000.0",
      "population_z": "3130000.0",
      "urban_population_z": "188000.0",
      "urban_population_growth_rate_z": "0.0",
      "cinc_score_z": "0.0013172193",
      "land_mass_exchange_gain_z": "0.0",
      "population_exchange_gain_z": "0.0",
      "land_mass_exchange_loss_z": "0.0",
      "population_exchange_loss_z": "0.0",
      "refugees_originated_z": "0.0",
      "refugees_hosted_z": "0.0",
      "internally_displaced_persons_z": "0.0",
      "concurrent_wars_z": "1.0"
    },
    {
      "id": "6",
      "war_type_code": "4",
      "c_code": "740",
      "participant": "Japan",
      "side": "2.0",
      "battle_deaths_z": "1500.0",
      "battle_deaths_estimated": "0",
      "start_year": "1918",
      "start_date": "1918-08-03",
      "end_year": "1920.0",
      "end_date": "1920-10-15",
      "ongoing_conflict": "0",
      "start_date_estimated": "0",
      "end_date_estimated": "0",
      "days_not_at_war_z": "0.0",
      "lagging_war": "-8",
      "leading_war": "-8",
      "deaths_both_sides": "nan",
      "peak_forces_available_z": "660000.0",
      "peak_battle_forces_z": "74000.0",
      "terrorism_deaths_x": "0.0",
      "mid_dyads_x": "2.0",
      "mid_dyads_initiated_x": "2.0",
      "mid_dyads_targeted_x": "0.0",
      "mid_dyads_joined_x": "0.0",
      "allied_countries_x": "1.0",
      "trade_countries_x": "2.0",
      "money_flow_in_x": "194020000.0",
      "money_flow_out_x": "239590000.0",
      "imports_x": "1006.35",
      "exports_x": "1142.33",
      "military_expenditure_x": "298716000.0",
      "military_personnel_x": "660000.0",
      "iron_steel_production_x": "1626000000.0",
      "energy_consumption_x": "59814000000.0",
      "population_x": "54739000.0",
      "urban_population_x": "7340000.0",
      "urban_population_growth_rate_x": "0.0",
      "cinc_score_x": "0.02928555",
      "land_mass_exchange_gain_x": "0.0",
      "population_exchange_gain_x": "0.0",
      "land_mass_exchange_loss_x": "0.0",
      "population_exchange_loss_x": "0.0",
      "refugees_originated_x": "0.0",
      "refugees_hosted_x": "0.0",
      "internally_displaced_persons_x": "0.0",
      "concurrent_wars_x": "1.0",
      "terrorism_deaths_y": "0.0",
      "mid_dyads_y": "4.0",
      "mid_dyads_initiated_y": "4.0",
      "mid_dyads_targeted_y": "0.0",
      "mid_dyads_joined_y": "0.0",
      "allied_countries_y": "1.0",
      "trade_countries_y": "31.0",
      "money_flow_in_y": "777890000.0",
      "money_flow_out_y": "868700000.0",
      "imports_y": "1181.82",
      "exports_y": "984.85",
      "military_expenditure_y": "449471000.0",
      "military_personnel_y": "306000.0",
      "iron_steel_production_y": "1682000000.0",
      "energy_consumption_y": "62634000000.0",
      "population_y": "55936000.0",
      "urban_population_y": "7734000.0",
      "urban_population_growth_rate_y": "0.0",
      "cinc_score_y": "0.040832121",
      "land_mass_exchange_gain_y": "2476.0",
      "population_exchange_gain_y": "2476.0",
      "land_mass_exchange_loss_y": "0.0",
      "population_exchange_loss_y": "0.0",
      "refugees_originated_y": "0.0",
      "refugees_hosted_y": "0.0",
      "internally_displaced_persons_y": "0.0",
      "concurrent_wars_y": "0.0",
      "terrorism_deaths_z": "0.0",
      "mid_dyads_z": "3.67",
      "mid_dyads_initiated_z": "3.67",
      "mid_dyads_targeted_z": "0.0",
      "mid_dyads_joined_z": "0.0",
      "allied_countries_z": "1.0",
      "trade_countries_z": "18.0",
      "money_flow_in_z": "568880000.0",
      "money_flow_out_z": "700160000.0",
      "imports_z": "1156.91",
      "exports_z": "1115.73",
      "military_expenditure_z": "394605330.0",
      "military_personnel_z": "424000.0",
      "iron_steel_production_z": "1645340000.0",
      "energy_consumption_z": "62953340000.0",
      "population_z": "55236000.0",
      "urban_population_z": "7531330.0",
      "urban_population_growth_rate_z": "0.0",
      "cinc_score_z": "0.034961667",
      "land_mass_exchange_gain_z": "2476.0",
      "population_exchange_gain_z": "2476.0",
      "land_mass_exchange_loss_z": "0.0",
      "population_exchange_loss_z": "0.0",
      "refugees_originated_z": "0.0",
      "refugees_hosted_z": "0.0",
      "internally_displaced_persons_z": "0.0",
      "concurrent_wars_z": "1.0"
    }
  ],
  "links": [
    {
      "source": "0",
      "target": "4",
      "territory_exchange_x": "0.0",
      "colonial_contiguity_x": "0.0",
      "contiguity_x": "0.0",
      "alliance_x": "0.0",
      "defense_cooperation_agreements_x": "0.0",
      "inter_governmental_organizations_x": "0.0",
      "diplomatic_exchange_x": "0.0",
      "trade_relations_x": "0.0",
      "same_leader_type_x": "0.0",
      "military_leaders_x": "0.0",
      "communist_leaders_x": "0.0",
      "democratic_regimes_x": "0.0",
      "dictatorships_x": "0.0",
      "direct_election_x": "0.0",
      "indirect_election_x": "0.0",
      "non_elected_leaders_x": "0.0",
      "no_legislature_x": "0.0",
      "non_elective_legislature_x": "0.0",
      "elective_legislature_x": "0.0",
      "no_partisan_legislature_legal_x": "0.0",
      "no_non_regime_legislature_parties_legal_x": "0.0",
      "multi_party_legislature_legal_x": "0.0",
      "all_parties_illegal_x": "0.0",
      "single_party_state_exists_x": "0.0",
      "multi_party_state_exists_x": "0.0",
      "no_parties_exist_x": "0.0",
      "one_party_exists_x": "0.0",
      "no_non_regime_parties_exist_x": "0.0",
      "new_leader_x": "0.0",
      "atop_x": "0.0",
      "mtops_x": "0.0",
      "territory_exchange_y": "0.0",
      "colonial_contiguity_y": "0.0",
      "contiguity_y": "0.0",
      "alliance_y": "0.0",
      "defense_cooperation_agreements_y": "0.0",
      "inter_governmental_organizations_y": "0.0",
      "diplomatic_exchange_y": "0.0",
      "trade_relations_y": "0.0",
      "same_leader_type_y": "0.0",
      "military_leaders_y": "0.0",
      "communist_leaders_y": "0.0",
      "democratic_regimes_y": "0.0",
      "dictatorships_y": "0.0",
      "direct_election_y": "0.0",
      "indirect_election_y": "0.0",
      "non_elected_leaders_y": "0.0",
      "no_legislature_y": "0.0",
      "non_elective_legislature_y": "0.0",
      "elective_legislature_y": "0.0",
      "no_partisan_legislature_legal_y": "0.0",
      "no_non_regime_legislature_parties_legal_y": "0.0",
      "multi_party_legislature_legal_y": "0.0",
      "all_parties_illegal_y": "0.0",
      "single_party_state_exists_y": "0.0",
      "multi_party_state_exists_y": "0.0",
      "no_parties_exist_y": "0.0",
      "one_party_exists_y": "0.0",
      "no_non_regime_parties_exist_y": "0.0",
      "new_leader_y": "0.0",
      "atop_y": "0.0",
      "mtops_y": "0.0",
      "territory_exchange_z": "0.0",
      "colonial_contiguity_z": "0.0",
      "contiguity_z": "0.0",
      "alliance_z": "0.0",
      "defense_cooperation_agreements_z": "0.0",
      "inter_governmental_organizations_z": "0.0",
      "diplomatic_exchange_z": "0.0",
      "trade_relations_z": "0.0",
      "same_leader_type_z": "0.0",
      "military_leaders_z": "0.0",
      "communist_leaders_z": "0.0",
      "democratic_regimes_z": "0.0",
      "dictatorships_z": "0.0",
      "direct_election_z": "0.0",
      "indirect_election_z": "0.0",
      "non_elected_leaders_z": "0.0",
      "no_legislature_z": "0.0",
      "non_elective_legislature_z": "0.0",
      "elective_legislature_z": "0.0",
      "no_partisan_legislature_legal_z": "0.0",
      "no_non_regime_legislature_parties_legal_z": "0.0",
      "multi_party_legislature_legal_z": "0.0",
      "all_parties_illegal_z": "0.0",
      "single_party_state_exists_z": "0.0",
      "multi_party_state_exists_z": "0.0",
      "no_parties_exist_z": "0.0",
      "one_party_exists_z": "0.0",
      "no_non_regime_parties_exist_z": "0.0",
      "new_leader_z": "0.0",
      "atop_z": "0.0",
      "mtops_z": "0.0"
    },
    {
      "source": "1",
      "target": "4",
      "territory_exchange_x": "0.0",
      "colonial_contiguity_x": "1.0",
      "contiguity_x": "0.0",
      "alliance_x": "0.0",
      "defense_cooperation_agreements_x": "0.0",
      "inter_governmental_organizations_x": "1.0",
      "diplomatic_exchange_x": "0.0",
      "trade_relations_x": "0.0",
      "same_leader_type_x": "0.0",
      "military_leaders_x": "0.0",
      "communist_leaders_x": "0.0",
      "democratic_regimes_x": "0.0",
      "dictatorships_x": "0.0",
      "direct_election_x": "0.0",
      "indirect_election_x": "0.0",
      "non_elected_leaders_x": "0.0",
      "no_legislature_x": "0.0",
      "non_elective_legislature_x": "0.0",
      "elective_legislature_x": "0.0",
      "no_partisan_legislature_legal_x": "0.0",
      "no_non_regime_legislature_parties_legal_x": "0.0",
      "multi_party_legislature_legal_x": "0.0",
      "all_parties_illegal_x": "0.0",
      "single_party_state_exists_x": "0.0",
      "multi_party_state_exists_x": "0.0",
      "no_parties_exist_x": "0.0",
      "one_party_exists_x": "0.0",
      "no_non_regime_parties_exist_x": "0.0",
      "new_leader_x": "0.0",
      "atop_x": "0.0",
      "mtops_x": "0.0",
      "territory_exchange_y": "0.0",
      "colonial_contiguity_y": "1.0",
      "contiguity_y": "0.0",
      "alliance_y": "0.0",
      "defense_cooperation_agreements_y": "0.0",
      "inter_governmental_organizations_y": "1.0",
      "diplomatic_exchange_y": "1.0",
      "trade_relations_y": "1.0",
      "same_leader_type_y": "0.0",
      "military_leaders_y": "0.0",
      "communist_leaders_y": "0.0",
      "democratic_regimes_y": "0.0",
      "dictatorships_y": "0.0",
      "direct_election_y": "0.0",
      "indirect_election_y": "0.0",
      "non_elected_leaders_y": "0.0",
      "no_legislature_y": "0.0",
      "non_elective_legislature_y": "0.0",
      "elective_legislature_y": "0.0",
      "no_partisan_legislature_legal_y": "0.0",
      "no_non_regime_legislature_parties_legal_y": "0.0",
      "multi_party_legislature_legal_y": "0.0",
      "all_parties_illegal_y": "0.0",
      "single_party_state_exists_y": "0.0",
      "multi_party_state_exists_y": "0.0",
      "no_parties_exist_y": "0.0",
      "one_party_exists_y": "0.0",
      "no_non_regime_parties_exist_y": "0.0",
      "new_leader_y": "0.0",
      "atop_y": "0.0",
      "mtops_y": "0.0",
      "territory_exchange_z": "0.0",
      "colonial_contiguity_z": "1.0",
      "contiguity_z": "0.0",
      "alliance_z": "0.0",
      "defense_cooperation_agreements_z": "0.0",
      "inter_governmental_organizations_z": "1.0",
      "diplomatic_exchange_z": "1.0",
      "trade_relations_z": "1.0",
      "same_leader_type_z": "0.0",
      "military_leaders_z": "0.0",
      "communist_leaders_z": "0.0",
      "democratic_regimes_z": "0.0",
      "dictatorships_z": "0.0",
      "direct_election_z": "0.0",
      "indirect_election_z": "0.0",
      "non_elected_leaders_z": "0.0",
      "no_legislature_z": "0.0",
      "non_elective_legislature_z": "0.0",
      "elective_legislature_z": "0.0",
      "no_partisan_legislature_legal_z": "0.0",
      "no_non_regime_legislature_parties_legal_z": "0.0",
      "multi_party_legislature_legal_z": "0.0",
      "all_parties_illegal_z": "0.0",
      "single_party_state_exists_z": "0.0",
      "multi_party_state_exists_z": "0.0",
      "no_parties_exist_z": "0.0",
      "one_party_exists_z": "0.0",
      "no_non_regime_parties_exist_z": "0.0",
      "new_leader_z": "0.0",
      "atop_z": "0.0",
      "mtops_z": "0.0"
    },
    {
      "source": "2",
      "target": "4",
      "territory_exchange_x": "0.0",
      "colonial_contiguity_x": "0.0",
      "contiguity_x": "0.0",
      "alliance_x": "0.0",
      "defense_cooperation_agreements_x": "0.0",
      "inter_governmental_organizations_x": "1.0",
      "diplomatic_exchange_x": "0.0",
      "trade_relations_x": "0.0",
      "same_leader_type_x": "0.0",
      "military_leaders_x": "0.0",
      "communist_leaders_x": "0.0",
      "democratic_regimes_x": "0.0",
      "dictatorships_x": "0.0",
      "direct_election_x": "0.0",
      "indirect_election_x": "0.0",
      "non_elected_leaders_x": "0.0",
      "no_legislature_x": "0.0",
      "non_elective_legislature_x": "0.0",
      "elective_legislature_x": "0.0",
      "no_partisan_legislature_legal_x": "0.0",
      "no_non_regime_legislature_parties_legal_x": "0.0",
      "multi_party_legislature_legal_x": "0.0",
      "all_parties_illegal_x": "0.0",
      "single_party_state_exists_x": "0.0",
      "multi_party_state_exists_x": "0.0",
      "no_parties_exist_x": "0.0",
      "one_party_exists_x": "0.0",
      "no_non_regime_parties_exist_x": "0.0",
      "new_leader_x": "0.0",
      "atop_x": "0.0",
      "mtops_x": "0.0",
      "territory_exchange_y": "0.0",
      "colonial_contiguity_y": "0.0",
      "contiguity_y": "0.0",
      "alliance_y": "0.0",
      "defense_cooperation_agreements_y": "0.0",
      "inter_governmental_organizations_y": "1.0",
      "diplomatic_exchange_y": "1.0",
      "trade_relations_y": "1.0",
      "same_leader_type_y": "0.0",
      "military_leaders_y": "0.0",
      "communist_leaders_y": "0.0",
      "democratic_regimes_y": "0.0",
      "dictatorships_y": "0.0",
      "direct_election_y": "0.0",
      "indirect_election_y": "0.0",
      "non_elected_leaders_y": "0.0",
      "no_legislature_y": "0.0",
      "non_elective_legislature_y": "0.0",
      "elective_legislature_y": "0.0",
      "no_partisan_legislature_legal_y": "0.0",
      "no_non_regime_legislature_parties_legal_y": "0.0",
      "multi_party_legislature_legal_y": "0.0",
      "all_parties_illegal_y": "0.0",
      "single_party_state_exists_y": "0.0",
      "multi_party_state_exists_y": "0.0",
      "no_parties_exist_y": "0.0",
      "one_party_exists_y": "0.0",
      "no_non_regime_parties_exist_y": "0.0",
      "new_leader_y": "0.0",
      "atop_y": "0.0",
      "mtops_y": "0.0",
      "territory_exchange_z": "0.0",
      "colonial_contiguity_z": "0.0",
      "contiguity_z": "0.0",
      "alliance_z": "0.0",
      "defense_cooperation_agreements_z": "0.0",
      "inter_governmental_organizations_z": "1.0",
      "diplomatic_exchange_z": "1.0",
      "trade_relations_z": "1.0",
      "same_leader_type_z": "0.0",
      "military_leaders_z": "0.0",
      "communist_leaders_z": "0.0",
      "democratic_regimes_z": "0.0",
      "dictatorships_z": "0.0",
      "direct_election_z": "0.0",
      "indirect_election_z": "0.0",
      "non_elected_leaders_z": "0.0",
      "no_legislature_z": "0.0",
      "non_elective_legislature_z": "0.0",
      "elective_legislature_z": "0.0",
      "no_partisan_legislature_legal_z": "0.0",
      "no_non_regime_legislature_parties_legal_z": "0.0",
      "multi_party_legislature_legal_z": "0.0",
      "all_parties_illegal_z": "0.0",
      "single_party_state_exists_z": "0.0",
      "multi_party_state_exists_z": "0.0",
      "no_parties_exist_z": "0.0",
      "one_party_exists_z": "0.0",
      "no_non_regime_parties_exist_z": "0.0",
      "new_leader_z": "0.0",
      "atop_z": "0.0",
      "mtops_z": "0.0"
    },
    {
      "source": "3",
      "target": "4",
      "territory_exchange_x": "0.0",
      "colonial_contiguity_x": "0.0",
      "contiguity_x": "0.0",
      "alliance_x": "0.0",
      "defense_cooperation_agreements_x": "0.0",
      "inter_governmental_organizations_x": "1.0",
      "diplomatic_exchange_x": "0.0",
      "trade_relations_x": "0.0",
      "same_leader_type_x": "0.0",
      "military_leaders_x": "0.0",
      "communist_leaders_x": "0.0",
      "democratic_regimes_x": "0.0",
      "dictatorships_x": "0.0",
      "direct_election_x": "0.0",
      "indirect_election_x": "0.0",
      "non_elected_leaders_x": "0.0",
      "no_legislature_x": "0.0",
      "non_elective_legislature_x": "0.0",
      "elective_legislature_x": "0.0",
      "no_partisan_legislature_legal_x": "0.0",
      "no_non_regime_legislature_parties_legal_x": "0.0",
      "multi_party_legislature_legal_x": "0.0",
      "all_parties_illegal_x": "0.0",
      "single_party_state_exists_x": "0.0",
      "multi_party_state_exists_x": "0.0",
      "no_parties_exist_x": "0.0",
      "one_party_exists_x": "0.0",
      "no_non_regime_parties_exist_x": "0.0",
      "new_leader_x": "0.0",
      "atop_x": "0.0",
      "mtops_x": "0.0",
      "territory_exchange_y": "0.0",
      "colonial_contiguity_y": "0.0",
      "contiguity_y": "0.0",
      "alliance_y": "0.0",
      "defense_cooperation_agreements_y": "0.0",
      "inter_governmental_organizations_y": "1.0",
      "diplomatic_exchange_y": "0.0",
      "trade_relations_y": "1.0",
      "same_leader_type_y": "0.0",
      "military_leaders_y": "0.0",
      "communist_leaders_y": "0.0",
      "democratic_regimes_y": "0.0",
      "dictatorships_y": "0.0",
      "direct_election_y": "0.0",
      "indirect_election_y": "0.0",
      "non_elected_leaders_y": "0.0",
      "no_legislature_y": "0.0",
      "non_elective_legislature_y": "0.0",
      "elective_legislature_y": "0.0",
      "no_partisan_legislature_legal_y": "0.0",
      "no_non_regime_legislature_parties_legal_y": "0.0",
      "multi_party_legislature_legal_y": "0.0",
      "all_parties_illegal_y": "0.0",
      "single_party_state_exists_y": "0.0",
      "multi_party_state_exists_y": "0.0",
      "no_parties_exist_y": "0.0",
      "one_party_exists_y": "0.0",
      "no_non_regime_parties_exist_y": "0.0",
      "new_leader_y": "0.0",
      "atop_y": "0.0",
      "mtops_y": "0.0",
      "territory_exchange_z": "0.0",
      "colonial_contiguity_z": "0.0",
      "contiguity_z": "0.0",
      "alliance_z": "0.0",
      "defense_cooperation_agreements_z": "0.0",
      "inter_governmental_organizations_z": "1.0",
      "diplomatic_exchange_z": "0.0",
      "trade_relations_z": "1.0",
      "same_leader_type_z": "0.0",
      "military_leaders_z": "0.0",
      "communist_leaders_z": "0.0",
      "democratic_regimes_z": "0.0",
      "dictatorships_z": "0.0",
      "direct_election_z": "0.0",
      "indirect_election_z": "0.0",
      "non_elected_leaders_z": "0.0",
      "no_legislature_z": "0.0",
      "non_elective_legislature_z": "0.0",
      "elective_legislature_z": "0.0",
      "no_partisan_legislature_legal_z": "0.0",
      "no_non_regime_legislature_parties_legal_z": "0.0",
      "multi_party_legislature_legal_z": "0.0",
      "all_parties_illegal_z": "0.0",
      "single_party_state_exists_z": "0.0",
      "multi_party_state_exists_z": "0.0",
      "no_parties_exist_z": "0.0",
      "one_party_exists_z": "0.0",
      "no_non_regime_parties_exist_z": "0.0",
      "new_leader_z": "0.0",
      "atop_z": "0.0",
      "mtops_z": "0.0"
    },
    {
      "source": "4",
      "target": "5",
      "territory_exchange_x": "0.0",
      "colonial_contiguity_x": "0.0",
      "contiguity_x": "1.0",
      "alliance_x": "0.0",
      "defense_cooperation_agreements_x": "0.0",
      "inter_governmental_organizations_x": "1.0",
      "diplomatic_exchange_x": "0.0",
      "trade_relations_x": "0.0",
      "same_leader_type_x": "0.0",
      "military_leaders_x": "0.0",
      "communist_leaders_x": "0.0",
      "democratic_regimes_x": "0.0",
      "dictatorships_x": "0.0",
      "direct_election_x": "0.0",
      "indirect_election_x": "0.0",
      "non_elected_leaders_x": "0.0",
      "no_legislature_x": "0.0",
      "non_elective_legislature_x": "0.0",
      "elective_legislature_x": "0.0",
      "no_partisan_legislature_legal_x": "0.0",
      "no_non_regime_legislature_parties_legal_x": "0.0",
      "multi_party_legislature_legal_x": "0.0",
      "all_parties_illegal_x": "0.0",
      "single_party_state_exists_x": "0.0",
      "multi_party_state_exists_x": "0.0",
      "no_parties_exist_x": "0.0",
      "one_party_exists_x": "0.0",
      "no_non_regime_parties_exist_x": "0.0",
      "new_leader_x": "0.0",
      "atop_x": "0.0",
      "mtops_x": "0.0",
      "territory_exchange_y": "0.0",
      "colonial_contiguity_y": "0.0",
      "contiguity_y": "1.0",
      "alliance_y": "0.0",
      "defense_cooperation_agreements_y": "0.0",
      "inter_governmental_organizations_y": "1.0",
      "diplomatic_exchange_y": "0.0",
      "trade_relations_y": "0.0",
      "same_leader_type_y": "0.0",
      "military_leaders_y": "0.0",
      "communist_leaders_y": "0.0",
      "democratic_regimes_y": "0.0",
      "dictatorships_y": "0.0",
      "direct_election_y": "0.0",
      "indirect_election_y": "0.0",
      "non_elected_leaders_y": "0.0",
      "no_legislature_y": "0.0",
      "non_elective_legislature_y": "0.0",
      "elective_legislature_y": "0.0",
      "no_partisan_legislature_legal_y": "0.0",
      "no_non_regime_legislature_parties_legal_y": "0.0",
      "multi_party_legislature_legal_y": "0.0",
      "all_parties_illegal_y": "0.0",
      "single_party_state_exists_y": "0.0",
      "multi_party_state_exists_y": "0.0",
      "no_parties_exist_y": "0.0",
      "one_party_exists_y": "0.0",
      "no_non_regime_parties_exist_y": "0.0",
      "new_leader_y": "0.0",
      "atop_y": "0.0",
      "mtops_y": "0.0",
      "territory_exchange_z": "0.0",
      "colonial_contiguity_z": "0.0",
      "contiguity_z": "1.0",
      "alliance_z": "0.0",
      "defense_cooperation_agreements_z": "0.0",
      "inter_governmental_organizations_z": "1.0",
      "diplomatic_exchange_z": "0.0",
      "trade_relations_z": "0.0",
      "same_leader_type_z": "0.0",
      "military_leaders_z": "0.0",
      "communist_leaders_z": "0.0",
      "democratic_regimes_z": "0.0",
      "dictatorships_z": "0.0",
      "direct_election_z": "0.0",
      "indirect_election_z": "0.0",
      "non_elected_leaders_z": "0.0",
      "no_legislature_z": "0.0",
      "non_elective_legislature_z": "0.0",
      "elective_legislature_z": "0.0",
      "no_partisan_legislature_legal_z": "0.0",
      "no_non_regime_legislature_parties_legal_z": "0.0",
      "multi_party_legislature_legal_z": "0.0",
      "all_parties_illegal_z": "0.0",
      "single_party_state_exists_z": "0.0",
      "multi_party_state_exists_z": "0.0",
      "no_parties_exist_z": "0.0",
      "one_party_exists_z": "0.0",
      "no_non_regime_parties_exist_z": "0.0",
      "new_leader_z": "0.0",
      "atop_z": "0.0",
      "mtops_z": "0.0"
    },
    {
      "source": "4",
      "target": "6",
      "territory_exchange_x": "0.0",
      "colonial_contiguity_x": "1.0",
      "contiguity_x": "1.0",
      "alliance_x": "0.0",
      "defense_cooperation_agreements_x": "0.0",
      "inter_governmental_organizations_x": "1.0",
      "diplomatic_exchange_x": "0.0",
      "trade_relations_x": "1.0",
      "same_leader_type_x": "0.0",
      "military_leaders_x": "0.0",
      "communist_leaders_x": "0.0",
      "democratic_regimes_x": "0.0",
      "dictatorships_x": "0.0",
      "direct_election_x": "0.0",
      "indirect_election_x": "0.0",
      "non_elected_leaders_x": "0.0",
      "no_legislature_x": "0.0",
      "non_elective_legislature_x": "0.0",
      "elective_legislature_x": "0.0",
      "no_partisan_legislature_legal_x": "0.0",
      "no_non_regime_legislature_parties_legal_x": "0.0",
      "multi_party_legislature_legal_x": "0.0",
      "all_parties_illegal_x": "0.0",
      "single_party_state_exists_x": "0.0",
      "multi_party_state_exists_x": "0.0",
      "no_parties_exist_x": "0.0",
      "one_party_exists_x": "0.0",
      "no_non_regime_parties_exist_x": "0.0",
      "new_leader_x": "0.0",
      "atop_x": "0.0",
      "mtops_x": "0.0",
      "territory_exchange_y": "0.0",
      "colonial_contiguity_y": "1.0",
      "contiguity_y": "1.0",
      "alliance_y": "0.0",
      "defense_cooperation_agreements_y": "0.0",
      "inter_governmental_organizations_y": "1.0",
      "diplomatic_exchange_y": "1.0",
      "trade_relations_y": "1.0",
      "same_leader_type_y": "0.0",
      "military_leaders_y": "0.0",
      "communist_leaders_y": "0.0",
      "democratic_regimes_y": "0.0",
      "dictatorships_y": "0.0",
      "direct_election_y": "0.0",
      "indirect_election_y": "0.0",
      "non_elected_leaders_y": "0.0",
      "no_legislature_y": "0.0",
      "non_elective_legislature_y": "0.0",
      "elective_legislature_y": "0.0",
      "no_partisan_legislature_legal_y": "0.0",
      "no_non_regime_legislature_parties_legal_y": "0.0",
      "multi_party_legislature_legal_y": "0.0",
      "all_parties_illegal_y": "0.0",
      "single_party_state_exists_y": "0.0",
      "multi_party_state_exists_y": "0.0",
      "no_parties_exist_y": "0.0",
      "one_party_exists_y": "0.0",
      "no_non_regime_parties_exist_y": "0.0",
      "new_leader_y": "0.0",
      "atop_y": "0.0",
      "mtops_y": "0.0",
      "territory_exchange_z": "0.0",
      "colonial_contiguity_z": "1.0",
      "contiguity_z": "1.0",
      "alliance_z": "0.0",
      "defense_cooperation_agreements_z": "0.0",
      "inter_governmental_organizations_z": "1.0",
      "diplomatic_exchange_z": "1.0",
      "trade_relations_z": "1.0",
      "same_leader_type_z": "0.0",
      "military_leaders_z": "0.0",
      "communist_leaders_z": "0.0",
      "democratic_regimes_z": "0.0",
      "dictatorships_z": "0.0",
      "direct_election_z": "0.0",
      "indirect_election_z": "0.0",
      "non_elected_leaders_z": "0.0",
      "no_legislature_z": "0.0",
      "non_elective_legislature_z": "0.0",
      "elective_legislature_z": "0.0",
      "no_partisan_legislature_legal_z": "0.0",
      "no_non_regime_legislature_parties_legal_z": "0.0",
      "multi_party_legislature_legal_z": "0.0",
      "all_parties_illegal_z": "0.0",
      "single_party_state_exists_z": "0.0",
      "multi_party_state_exists_z": "0.0",
      "no_parties_exist_z": "0.0",
      "one_party_exists_z": "0.0",
      "no_non_regime_parties_exist_z": "0.0",
      "new_leader_z": "0.0",
      "atop_z": "0.0",
      "mtops_z": "0.0"
    }
  ]
}
